AUTHORS
CHANGELOG
LICENSE
MANIFEST.in
README.rst
setup.cfg
setup.py
page_size_check/__init__.py
page_size_check/pagesize_check.py
page_size_check/parser.py
page_size_check.egg-info/PKG-INFO
page_size_check.egg-info/SOURCES.txt
page_size_check.egg-info/dependency_links.txt
page_size_check.egg-info/requires.txt
page_size_check.egg-info/top_level.txt
page_size_check/__pycache__/__init__.cpython-35.pyc
page_size_check/__pycache__/parser.cpython-35.pyc
tests/__init__.py
tests/conftest.py
tests/unit/__init__.py
tests/unit/test_harfile_parser.py
tests/unit/test_unit.py