Metadata-Version: 1.2
Name: page-size-check
Version: 1.0.0
Summary: Utility to check the size of pages from a sitemap and its resources parsering the HAR file of request
Home-page: https://github.com/APSL/page-size-check
Author: Carlos Salom
Author-email: csalom@apsl.net
Maintainer: Carlos Salom
Maintainer-email: csalom@apsl.net
License: MIT
Platform: UNKNOWN
Classifier: Environment :: Console
Classifier: Intended Audience :: Developers
Classifier: Programming Language :: Python
Classifier: Programming Language :: Python :: 3
Classifier: Programming Language :: Python :: 3.5
Classifier: Programming Language :: Python :: 3.6
Classifier: Operating System :: OS Independent
Classifier: Topic :: Software Development
Classifier: Topic :: Software Development :: Libraries :: Python Modules
